LICENSE
tdf_tool/app.py
tdf_tool/modules/cli/bean/deps_item.py
tdf_tool/modules/cli/module_deps_rewrite.py
tdf_tool/modules/cli/project_cli.py
tdf_tool/modules/cli/utils/tree_analysis_utils.py
tdf_tool/modules/cli/utils/yaml_utils.py
tdf_tool/modules/config/config.py
tdf_tool/modules/config/initial_json_config.py
tdf_tool/modules/config/module_json_config.py
tdf_tool/modules/config/packages_config.py
tdf_tool/modules/fix_header/fix_header_entry.py
tdf_tool/modules/fix_header/fix_header_lint.py
tdf_tool/modules/fix_header/fix_header_lint_tool.py
tdf_tool/modules/fix_header/fix_header_replace_tool.py
tdf_tool/modules/gitlab/gitlab_utils.py
tdf_tool/modules/gitlab/python_gitlab_api.py
tdf_tool/modules/module/module_tools.py
tdf_tool/modules/multi_code/flutter/flutter_multi_code_lint.py
tdf_tool/modules/multi_code/flutter/flutter_multi_code_tools.py
tdf_tool/modules/multi_code/flutter/flutter_reflow.py
tdf_tool/modules/multi_code/i18n_lint.py
tdf_tool/modules/multi_code/ios/ios_i18n.py
tdf_tool/modules/multi_code/ios/ios_i18n_integrate.py
tdf_tool/modules/multi_code/ios/ios_i18n_lint.py
tdf_tool/modules/multi_code/ios/ios_i18n_reflow.py
tdf_tool/modules/multi_code/tools/file_util.py
tdf_tool/modules/multi_code/tools/i18n_request.py
tdf_tool/modules/multi_code/tools/ios_strings.py
tdf_tool/modules/multi_code/tools/reflow_file.py
tdf_tool/modules/multi_code/tools/reflow_server.py
tdf_tool/modules/multi_code/tools/serve_file.py
tdf_tool/modules/package/seal_off_package_utils.py
tdf_tool/modules/translate/file_util.py
tdf_tool/modules/translate/flutter/flutter_tranalate_interface.py
tdf_tool/modules/translate/flutter/flutter_translate_lint.py
tdf_tool/modules/translate/flutter/flutter_translate_lint_interface.py
tdf_tool/modules/translate/flutter/flutter_translate_tools.py
tdf_tool/modules/translate/flutter/resource/flutter_res_translate_lint.py
tdf_tool/modules/translate/flutter/resource/flutter_res_translate_tools.py
tdf_tool-2.5.70.dist-info/LICENSE
tdf_tool-2.5.70.dist-info/METADATA
tdf_tool-2.5.70.dist-info/WHEEL
tdf_tool-2.5.70.dist-info/entry_points.txt
tdf_tool-2.5.70.dist-info/RECORD
